gcloudoem/VERSION
gcloudoem/__init__.py
gcloudoem/entity.py
gcloudoem/exceptions.py
gcloudoem/key.py
gcloudoem/options.py
gcloudoem/properties.py
gcloudoem/utils.py
gcloudoem/base/__init__.py
gcloudoem/base/entity.py
gcloudoem/base/metaclasses.py
gcloudoem/base/properties.py
gcloudoem/datastore/__init__.py
gcloudoem/datastore/base.py
gcloudoem/datastore/connection.py
gcloudoem/datastore/credentials.py
gcloudoem/datastore/datastore_v1_pb2.py
gcloudoem/datastore/environment.py
gcloudoem/datastore/query.py
gcloudoem/datastore/transaction.py
gcloudoem/datastore/utils.py
gcloudoem/django/__init__.py
gcloudoem/django/auth.py
gcloudoem/django/shortcuts.py
gcloudoem/django/utils.py
gcloudoem/django/gcloud_auth/__init__.py
gcloudoem/django/gcloud_auth/models.py
gcloudoem/queryset/__init__.py
gcloudoem/queryset/lookups.py
gcloudoem/queryset/manager.py
gcloudoem-0.1.0rc15.dist-info/DESCRIPTION.rst
gcloudoem-0.1.0rc15.dist-info/METADATA
gcloudoem-0.1.0rc15.dist-info/RECORD
gcloudoem-0.1.0rc15.dist-info/WHEEL
gcloudoem-0.1.0rc15.dist-info/metadata.json
gcloudoem-0.1.0rc15.dist-info/top_level.txt
