Metadata-Version: 2.0
Name: gcloudoem
Version: 0.1.0rc15
Summary: gcloud-datastore-oem is a Python Object-Entity Mapper for working with Google Datastore.
Home-page: https://github.com/Kapiche/gcloud-datastore-oem
Author: Kapiche
Author-email: opensource@kapiche.com
License: Apache Software License
Platform: UNKNOWN
Classifier: Development Status :: 2 - Pre-Alpha
Classifier: Intended Audience :: Developers
Classifier: License :: OSI Approved :: Apache Software License
Classifier: Operating System :: OS Independent
Classifier: Programming Language :: Python
Classifier: Programming Language :: Python :: 2
Classifier: Programming Language :: Python :: 2.7
Classifier: Programming Language :: Python :: 3
Classifier: Programming Language :: Python :: 3.3
Classifier: Programming Language :: Python :: 3.4
Classifier: Programming Language :: Python :: Implementation :: CPython
Classifier: Topic :: Database
Classifier: Topic :: Software Development :: Libraries :: Python Modules
Requires-Dist: future
Requires-Dist: httplib2
Requires-Dist: oauth2client (>=1.4.7)
Requires-Dist: protobuf
Requires-Dist: pycrypto
Requires-Dist: pytz
Requires-Dist: six
Provides-Extra: dev
Requires-Dist: sphinx; extra == 'dev'
Requires-Dist: sphinx-rtd-theme; extra == 'dev'
Provides-Extra: test
Requires-Dist: nose; extra == 'test'
Requires-Dist: coverage; extra == 'test'
Requires-Dist: unittest2; extra == 'test'
Requires-Dist: django (>=1.5.1); extra == 'test'
Requires-Dist: pyOpenSSL; extra == 'test'
Provides-Extra: test-py2
Requires-Dist: nose; extra == 'test-py2'
Requires-Dist: coverage; extra == 'test-py2'
Requires-Dist: unittest2; extra == 'test-py2'
Requires-Dist: django (>=1.5.1); extra == 'test-py2'
Requires-Dist: pyOpenSSL; extra == 'test-py2'
Requires-Dist: mock; extra == 'test-py2'
